ds_get
