Metadata-Version: 2.1
Name: ds-get
Version: 0.1.1
Summary: ds_get - Synology DS Get console client
Home-page: https://github.com/dekomote/ds_get/
Author: Dejan Noveski
Author-email: dr.mote@gmail.com
License: MIT
Platform: UNKNOWN
Classifier: Development Status :: 4 - Beta
Classifier: License :: OSI Approved :: MIT License
Classifier: Programming Language :: Python :: 3
Classifier: Programming Language :: Python :: 3.6
Classifier: Programming Language :: Python :: 3.7
Classifier: Programming Language :: Python :: 3.8
License-File: LICENSE
License-File: AUTHORS.rst
